{
    "pubmed_id": "12782119",
    "pubmed_central_id": null,
    "doi": "10.1016/s0022-5193(03)00079-1",
    "authors": [
        "G. Lemon",
        "W.G. Gibson",
        "M.R. Bennett"
    ],
    "title": "Metabotropic receptor activation, desensitization and sequestration-I: modelling calcium and inositol 1,4,5-trisphosphate dynamics following receptor activation",
    "journal": "Journal of Theoretical Biology",
    "volume": "223",
    "issue": "1",
    "pages": "93-111",
    "year": "2003",
    "date": "2003-07-07"
}